README.rst
setup.py
test/test_vtk_visualizer.py
vtk_visualizer/QVTKRenderWindowInteractor.py
vtk_visualizer/__init__.py
vtk_visualizer/plot3d.py
vtk_visualizer/pointobject.py
vtk_visualizer/renderwidget.py
vtk_visualizer/visualizercontrol.py
vtk_visualizer.egg-info/PKG-INFO
vtk_visualizer.egg-info/SOURCES.txt
vtk_visualizer.egg-info/dependency_links.txt
vtk_visualizer.egg-info/top_level.txt