Metadata-Version: 1.1
Name: vtk-visualizer
Version: 0.9.6
Summary: Easy 3D visualization of point clouds and geometric primitives
Home-page: https://bitbucket.org/oskotheim/vtk_visualizer
Author: Oystein Skotheim
Author-email: oystein.skotheim@zividlabs.com
License: BSD
Platform: any
Classifier: Development Status :: 3 - Alpha
Classifier: Environment :: X11 Applications :: Qt
Classifier: Intended Audience :: Science/Research
Classifier: Intended Audience :: Developers
Classifier: License :: OSI Approved :: BSD License
Classifier: Programming Language :: Python
Classifier: Topic :: Scientific/Engineering :: Visualization
